numpy_da/__init__.py
numpy_da/dynamic_array.py
numpy_dynamic_array-0.0.1.dist-info/LICENSE.txt
numpy_dynamic_array-0.0.1.dist-info/METADATA
numpy_dynamic_array-0.0.1.dist-info/WHEEL
numpy_dynamic_array-0.0.1.dist-info/top_level.txt
numpy_dynamic_array-0.0.1.dist-info/RECORD
