Metadata-Version: 2.1
Name: numpy-dynamic-array
Version: 0.0.1
Summary: Create a numpy dynamic array.
Home-page: https://github.com/dylanwal/numpy_dynamic_array
Author: Dylan Walsh
License: BSD
Platform: any
Classifier: License :: OSI Approved :: BSD License
Classifier: Programming Language :: Python :: 3
Classifier: Programming Language :: Python :: 3 :: Only
Classifier: Programming Language :: Python :: 3.9
Requires-Python: >=3.9
License-File: LICENSE.txt
Requires-Dist: numpy (>=1.22.0)
Provides-Extra: testing
Requires-Dist: pytest (>=6.0) ; extra == 'testing'
Requires-Dist: pytest-cov (>=2.0) ; extra == 'testing'
Requires-Dist: mypy (>=0.910) ; extra == 'testing'
Requires-Dist: flake8 (>=3.9) ; extra == 'testing'
